{"_ts":[1525158283,1525209804],"_r":{"breakdown":{"html":{"bytes":[112978,160894],"requests":[8,10]},"js":{"bytes":[768966,768680],"requests":[42,42]},"css":{"bytes":[64004,64004],"requests":[1,1]},"image":{"bytes":[205929,229329],"requests":[75,73]},"flash":{"bytes":[0,0],"requests":[0,0]},"font":{"bytes":[81461,81463],"requests":[4,4]},"video":{"bytes":[0,0],"requests":[0,0]},"other":{"bytes":[0,0],"requests":[12,12]}},"date":[1525158283,1525209804],"domElements":[5277,5437],"domInteractive":[3009,3177],"firstPaint":[1292.2000000108,1355.9999999998],"fullyLoaded":[5557,5708],"id":["180501_RZ_0662cf07343d17cf8073243cb3b79c7d","180501_T8_f0c782112e3ff855dea27ff9028bb8ab"],"loadTime":[4748,4886],"render":[1300,1300],"SpeedIndex":[2378,2233],"TTFB":[718,729],"videoFrames":[[{"_i":"ms_000000.jpg","_t":0,"_vc":0},{"_i":"ms_001300.jpg","_t":1300,"_vc":35},{"_i":"ms_001400.jpg","_t":1400,"_vc":33},{"_i":"ms_001600.jpg","_t":1600,"_vc":33},{"_i":"ms_001700.jpg","_t":1700,"_vc":35},{"_i":"ms_001800.jpg","_t":1800,"_vc":46},{"_i":"ms_002100.jpg","_t":2100,"_vc":47},{"_i":"ms_002200.jpg","_t":2200,"_vc":47},{"_i":"ms_002900.jpg","_t":2900,"_vc":47},{"_i":"ms_003100.jpg","_t":3100,"_vc":86},{"_i":"ms_003300.jpg","_t":3300,"_vc":99},{"_i":"ms_003400.jpg","_t":3400,"_vc":99},{"_i":"ms_003600.jpg","_t":3600,"_vc":99},{"_i":"ms_003700.jpg","_t":3700,"_vc":99},{"_i":"ms_003900.jpg","_t":3900,"_vc":99},{"_i":"ms_004200.jpg","_t":4200,"_vc":99},{"_i":"ms_004400.jpg","_t":4400,"_vc":99},{"_i":"ms_004700.jpg","_t":4700,"_vc":99},{"_i":"ms_005000.jpg","_t":5000,"_vc":99},{"_i":"ms_005100.jpg","_t":5100,"_vc":99},{"_i":"ms_005200.jpg","_t":5200,"_vc":99},{"_i":"ms_005800.jpg","_t":5800,"_vc":99},{"_i":"ms_005900.jpg","_t":5900,"_vc":99},{"_i":"ms_006000.jpg","_t":6000,"_vc":100}],[{"_i":"ms_000000.jpg","_t":0,"_vc":0},{"_i":"ms_001300.jpg","_t":1300,"_vc":20},{"_i":"ms_001500.jpg","_t":1500,"_vc":18},{"_i":"ms_001600.jpg","_t":1600,"_vc":34},{"_i":"ms_001700.jpg","_t":1700,"_vc":34},{"_i":"ms_001800.jpg","_t":1800,"_vc":39},{"_i":"ms_001900.jpg","_t":1900,"_vc":40},{"_i":"ms_002100.jpg","_t":2100,"_vc":72},{"_i":"ms_002900.jpg","_t":2900,"_vc":73},{"_i":"ms_003200.jpg","_t":3200,"_vc":73},{"_i":"ms_003300.jpg","_t":3300,"_vc":73},{"_i":"ms_003400.jpg","_t":3400,"_vc":99},{"_i":"ms_003500.jpg","_t":3500,"_vc":99},{"_i":"ms_003700.jpg","_t":3700,"_vc":99},{"_i":"ms_003900.jpg","_t":3900,"_vc":99},{"_i":"ms_004200.jpg","_t":4200,"_vc":99},{"_i":"ms_004400.jpg","_t":4400,"_vc":99},{"_i":"ms_005200.jpg","_t":5200,"_vc":99},{"_i":"ms_005300.jpg","_t":5300,"_vc":100}]],"visualComplete":[6000,5300],"lighthouse":[54,54],"pagespeed":[65,63]}}