{"_ts":[1525158169,1525207548,1525246585],"_r":{"breakdown":{"html":{"bytes":[85362,85827,86393],"requests":[11,11,14]},"js":{"bytes":[1093191,1035109,1029412],"requests":[57,56,55]},"css":{"bytes":[152459,152209,152459],"requests":[2,2,2]},"image":{"bytes":[1095146,970801,971651],"requests":[61,56,57]},"flash":{"bytes":[0,0,0],"requests":[0,0,0]},"font":{"bytes":[134200,134200,134202],"requests":[6,6,6]},"video":{"bytes":[0,0,0],"requests":[0,0,0]},"other":{"bytes":[43792,45368,44250],"requests":[11,13,13]}},"date":[1525158169,1525207548,1525246585],"domElements":[2922,2922,2922],"domInteractive":[4389,3181,2954],"firstPaint":[2778.2999999981,2343.7999999987,2150.3000000084],"fullyLoaded":[9301,11633,8691],"id":["180501_MT_876753b3082411721c6f01734eba3e52","180501_HG_4106fb285a41b3fcc136f62b3f7253de","180502_88_95068cc29d27f5b70c240123e17d8930"],"loadTime":[6838,5869,5638],"render":[3200,2600,2400],"SpeedIndex":[3996,4158,3237],"TTFB":[559,643,496],"videoFrames":[[{"_i":"ms_000000.jpg","_t":0,"_vc":0},{"_i":"ms_003200.jpg","_t":3200,"_vc":14},{"_i":"ms_003300.jpg","_t":3300,"_vc":19},{"_i":"ms_003400.jpg","_t":3400,"_vc":19},{"_i":"ms_003800.jpg","_t":3800,"_vc":19},{"_i":"ms_003900.jpg","_t":3900,"_vc":31},{"_i":"ms_004200.jpg","_t":4200,"_vc":96},{"_i":"ms_004400.jpg","_t":4400,"_vc":97},{"_i":"ms_004700.jpg","_t":4700,"_vc":100},{"_i":"ms_004900.jpg","_t":4900,"_vc":100}],[{"_i":"ms_000000.jpg","_t":0,"_vc":0},{"_i":"ms_002600.jpg","_t":2600,"_vc":3},{"_i":"ms_002800.jpg","_t":2800,"_vc":18},{"_i":"ms_003000.jpg","_t":3000,"_vc":22},{"_i":"ms_003100.jpg","_t":3100,"_vc":22},{"_i":"ms_003200.jpg","_t":3200,"_vc":22},{"_i":"ms_003300.jpg","_t":3300,"_vc":22},{"_i":"ms_003600.jpg","_t":3600,"_vc":28},{"_i":"ms_003700.jpg","_t":3700,"_vc":28},{"_i":"ms_003800.jpg","_t":3800,"_vc":28},{"_i":"ms_004100.jpg","_t":4100,"_vc":28},{"_i":"ms_004200.jpg","_t":4200,"_vc":40},{"_i":"ms_004700.jpg","_t":4700,"_vc":100}],[{"_i":"ms_000000.jpg","_t":0,"_vc":0},{"_i":"ms_002400.jpg","_t":2400,"_vc":13},{"_i":"ms_002600.jpg","_t":2600,"_vc":13},{"_i":"ms_002700.jpg","_t":2700,"_vc":13},{"_i":"ms_002900.jpg","_t":2900,"_vc":14},{"_i":"ms_003100.jpg","_t":3100,"_vc":18},{"_i":"ms_003300.jpg","_t":3300,"_vc":70},{"_i":"ms_003400.jpg","_t":3400,"_vc":70},{"_i":"ms_003500.jpg","_t":3500,"_vc":99},{"_i":"ms_003700.jpg","_t":3700,"_vc":99},{"_i":"ms_003900.jpg","_t":3900,"_vc":99},{"_i":"ms_004100.jpg","_t":4100,"_vc":100}]],"visualComplete":[4700,4700,4100],"lighthouse":[45,45,45],"pagespeed":[61,64,64]}}