{"_ts":[1506859382],"_r":{"breakdown":{"html":{"bytes":[69261],"requests":[32]},"js":{"bytes":[1280184],"requests":[60]},"css":{"bytes":[119097],"requests":[2]},"image":{"bytes":[1455908],"requests":[92]},"flash":{"bytes":[0],"requests":[0]},"font":{"bytes":[123411],"requests":[6]},"other":{"bytes":[44708],"requests":[6]}},"date":[1506859382],"domElements":[3785],"domInteractive":[4649],"firstPaint":[4030],"fullyLoaded":[18047],"id":["171001_8F_a7d5e0cab9a837c42f75883f9b6b10b7"],"loadTime":[11590],"render":[4089],"SpeedIndex":[4955],"TTFB":[439],"videoFrames":[[{"_i":"frame_0000.jpg","_t":0,"_vc":0},{"_i":"frame_0041.jpg","_t":4100,"_vc":25},{"_i":"frame_0044.jpg","_t":4400,"_vc":36},{"_i":"frame_0047.jpg","_t":4700,"_vc":36},{"_i":"frame_0052.jpg","_t":5200,"_vc":41},{"_i":"frame_0054.jpg","_t":5400,"_vc":100}]],"visualComplete":[5400],"lighthouse":[null],"pagespeed":[57]}}